gocomics.py
setup.py
gocomics.egg-info/PKG-INFO
gocomics.egg-info/SOURCES.txt
gocomics.egg-info/dependency_links.txt
gocomics.egg-info/entry_points.txt
gocomics.egg-info/not-zip-safe
gocomics.egg-info/requires.txt
gocomics.egg-info/top_level.txt