Metadata-Version: 1.1
Name: gocomics
Version: 0.0.1
Summary: downloader of gocomics comics
Home-page: https://github.com/tiagocoutinho/gocomics
Author: Tiago Coutinho
Author-email: coutinhotiago@gmail.com
License: UNKNOWN
Keywords: gocomics,comics
Platform: UNKNOWN
Classifier: Programming Language :: Python :: 2.6
Classifier: Programming Language :: Python :: 2.7
Classifier: Programming Language :: Python :: 3.4
Classifier: Programming Language :: Python :: 3.5
Classifier: Programming Language :: Python :: 3.6
